{
  "type": "minecraft:simple_block",
  "config": {
    "to_place": {
      "type": "minecraft:weighted_state_provider",
      "entries": [
        {
          "data": {
            "Name": "minecraft:short_grass"
          },
          "weight": 5
        },
        {
          "data": {
            "Name": "minecraft:tall_grass"
          },
          "weight": 10
        },
        {
          "data": {
            "Name": "cropcritters:strangle_fern",
            "Properties": {
              "age": "1"
            }
          },
          "weight": 1
        }
      ]
    }
  }
}